mcpeer/__init__.py
mcpeer/session.py
mcpeer/types.py
mcpeer/agents/__init__.py
mcpeer/agents/base.py
mcpeer/agents/langchain_agent.py
mcpeer/agents/mcpagent.py
mcpeer/connectors/__init__.py
mcpeer/connectors/base.py
mcpeer/connectors/http.py
mcpeer/connectors/stdio.py
mcpeer/connectors/websocket.py
mcpeer/tools/__init__.py
mcpeer/tools/converter.py
mcpeer/tools/formats.py
mcpeer-0.1.0.dist-info/licenses/LICENSE
mcpeer-0.1.0.dist-info/METADATA
mcpeer-0.1.0.dist-info/WHEEL
mcpeer-0.1.0.dist-info/top_level.txt
mcpeer-0.1.0.dist-info/RECORD
