Metadata-Version: 2.4
Name: mcpeer
Version: 0.1.0
Summary: Model-Agnostic MCP Library for LLMs
Home-page: https://github.com/pietrozullo/mcpeer
Author: Pietro Zullo
Author-email: pietro.zullo@gmail.com
Classifier: Development Status :: 3 - Alpha
Classifier: Intended Audience :: Developers
Classifier: License :: OSI Approved :: MIT License
Classifier: Operating System :: OS Independent
Classifier: Programming Language :: Python :: 3
Classifier: Programming Language :: Python :: 3.11
Classifier: Programming Language :: Python :: 3.12
Classifier: Topic :: Software Development :: Libraries :: Python Modules
Requires-Python: >=3.11
License-File: LICENSE
Requires-Dist: mcp
Requires-Dist: langchain>=0.1.0
Requires-Dist: langchain-community>=0.0.10
Requires-Dist: websockets>=12.0
Requires-Dist: aiohttp>=3.9.0
Requires-Dist: pydantic>=2.0.0
Requires-Dist: typing-extensions>=4.8.0
Requires-Dist: jsonschema-pydantic>=0.1.0
Requires-Dist: python-dotenv>=1.0.0
Provides-Extra: dev
Requires-Dist: pytest>=7.4.0; extra == "dev"
Requires-Dist: pytest-asyncio>=0.21.0; extra == "dev"
Requires-Dist: pytest-cov>=4.1.0; extra == "dev"
Requires-Dist: black>=23.9.0; extra == "dev"
Requires-Dist: isort>=5.12.0; extra == "dev"
Requires-Dist: mypy>=1.5.0; extra == "dev"
Requires-Dist: ruff>=0.1.0; extra == "dev"
Provides-Extra: anthropic
Requires-Dist: anthropic>=0.15.0; extra == "anthropic"
Provides-Extra: openai
Requires-Dist: openai>=1.10.0; extra == "openai"
Dynamic: author
Dynamic: author-email
Dynamic: classifier
Dynamic: description
Dynamic: description-content-type
Dynamic: home-page
Dynamic: license-file
Dynamic: provides-extra
Dynamic: requires-dist
Dynamic: requires-python
Dynamic: summary
